@[translated]
module tests

// empty enum
const jvm_acc_public = 1
const jvm_acc_private = 2
const jvm_acc_protected = 4
const jvm_acc_static = 8
const jvm_acc_final = 16
const jvm_acc_synchronized = 32
const jvm_acc_super = 32
const jvm_acc_volatile = 64
const jvm_acc_bridge = 64
const jvm_acc_transient = 128
const jvm_acc_varargs = 128
const jvm_acc_native = 256
const jvm_acc_interface = 512
const jvm_acc_abstract = 1024
const jvm_acc_strict = 2048
const jvm_acc_synthetic = 4096
const jvm_acc_annotation = 8192
const jvm_acc_enum = 16384
const jvm_acc_module = 32768

// empty enum
const jvm_t_boolean = 4
const jvm_t_char = 5
const jvm_t_float = 6
const jvm_t_double = 7
const jvm_t_byte = 8
const jvm_t_short = 9
const jvm_t_int = 10
const jvm_t_long = 11

// empty enum
const jvm_constant_utf8 = 1
const jvm_constant_unicode = 2
const jvm_constant_integer = 3
const jvm_constant_float = 4
const jvm_constant_long = 5
const jvm_constant_double = 6
const jvm_constant_class = 7
const jvm_constant_string = 8
const jvm_constant_fieldref = 9
const jvm_constant_methodref = 10
const jvm_constant_interface_methodref = 11
const jvm_constant_name_and_type = 12
const jvm_constant_method_handle = 15
const jvm_constant_method_type = 16
const jvm_constant_dynamic = 17
const jvm_constant_invoke_dynamic = 18
const jvm_constant_module = 19
const jvm_constant_package = 20
const jvm_constant_external_max = 20

// empty enum
const jvm_ref_get_field = 1
const jvm_ref_get_static = 2
const jvm_ref_put_field = 3
const jvm_ref_put_static = 4
const jvm_ref_invoke_virtual = 5
const jvm_ref_invoke_static = 6
const jvm_ref_invoke_special = 7
const jvm_ref_new_invoke_special = 8
const jvm_ref_invoke_interface = 9

// empty enum
const jvm_item_top = 0
const jvm_item_integer = 1
const jvm_item_float = 2
const jvm_item_double = 3
const jvm_item_long = 4
const jvm_item_null = 5
const jvm_item_uninitialized_this = 6
const jvm_item_object = 7
const jvm_item_uninitialized = 8

// empty enum
const jvm_signature_slash = `/`
const jvm_signature_dot = `.`
const jvm_signature_special = `<`
const jvm_signature_endspecial = `>`
const jvm_signature_array = `[`
const jvm_signature_byte = `B`
const jvm_signature_char = `C`
const jvm_signature_class = `L`
const jvm_signature_endclass = `;`
const jvm_signature_enum = `E`
const jvm_signature_float = `F`
const jvm_signature_double = `D`
const jvm_signature_func = `(`
const jvm_signature_endfunc = `)`
const jvm_signature_int = `I`
const jvm_signature_long = `J`
const jvm_signature_short = `S`
const jvm_signature_void = `V`
const jvm_signature_boolean = `Z`

// empty enum
const jvm_opc_nop = 0
const jvm_opc_aconst_null = 1
const jvm_opc_iconst_m1 = 2
const jvm_opc_iconst_0 = 3
const jvm_opc_iconst_1 = 4
const jvm_opc_iconst_2 = 5
const jvm_opc_iconst_3 = 6
const jvm_opc_iconst_4 = 7
const jvm_opc_iconst_5 = 8
const jvm_opc_lconst_0 = 9
const jvm_opc_lconst_1 = 10
const jvm_opc_fconst_0 = 11
const jvm_opc_fconst_1 = 12
const jvm_opc_fconst_2 = 13
const jvm_opc_dconst_0 = 14
const jvm_opc_dconst_1 = 15
const jvm_opc_bipush = 16
const jvm_opc_sipush = 17
const jvm_opc_ldc = 18
const jvm_opc_ldc_w = 19
const jvm_opc_ldc2_w = 20
const jvm_opc_iload = 21
const jvm_opc_lload = 22
const jvm_opc_fload = 23
const jvm_opc_dload = 24
const jvm_opc_aload = 25
const jvm_opc_iload_0 = 26
const jvm_opc_iload_1 = 27
const jvm_opc_iload_2 = 28
const jvm_opc_iload_3 = 29
const jvm_opc_lload_0 = 30
const jvm_opc_lload_1 = 31
const jvm_opc_lload_2 = 32
const jvm_opc_lload_3 = 33
const jvm_opc_fload_0 = 34
const jvm_opc_fload_1 = 35
const jvm_opc_fload_2 = 36
const jvm_opc_fload_3 = 37
const jvm_opc_dload_0 = 38
const jvm_opc_dload_1 = 39
const jvm_opc_dload_2 = 40
const jvm_opc_dload_3 = 41
const jvm_opc_aload_0 = 42
const jvm_opc_aload_1 = 43
const jvm_opc_aload_2 = 44
const jvm_opc_aload_3 = 45
const jvm_opc_iaload = 46
const jvm_opc_laload = 47
const jvm_opc_faload = 48
const jvm_opc_daload = 49
const jvm_opc_aaload = 50
const jvm_opc_baload = 51
const jvm_opc_caload = 52
const jvm_opc_saload = 53
const jvm_opc_istore = 54
const jvm_opc_lstore = 55
const jvm_opc_fstore = 56
const jvm_opc_dstore = 57
const jvm_opc_astore = 58
const jvm_opc_istore_0 = 59
const jvm_opc_istore_1 = 60
const jvm_opc_istore_2 = 61
const jvm_opc_istore_3 = 62
const jvm_opc_lstore_0 = 63
const jvm_opc_lstore_1 = 64
const jvm_opc_lstore_2 = 65
const jvm_opc_lstore_3 = 66
const jvm_opc_fstore_0 = 67
const jvm_opc_fstore_1 = 68
const jvm_opc_fstore_2 = 69
const jvm_opc_fstore_3 = 70
const jvm_opc_dstore_0 = 71
const jvm_opc_dstore_1 = 72
const jvm_opc_dstore_2 = 73
const jvm_opc_dstore_3 = 74
const jvm_opc_astore_0 = 75
const jvm_opc_astore_1 = 76
const jvm_opc_astore_2 = 77
const jvm_opc_astore_3 = 78
const jvm_opc_iastore = 79
const jvm_opc_lastore = 80
const jvm_opc_fastore = 81
const jvm_opc_dastore = 82
const jvm_opc_aastore = 83
const jvm_opc_bastore = 84
const jvm_opc_castore = 85
const jvm_opc_sastore = 86
const jvm_opc_pop = 87
const jvm_opc_pop2 = 88
const jvm_opc_dup = 89
const jvm_opc_dup_x1 = 90
const jvm_opc_dup_x2 = 91
const jvm_opc_dup2 = 92
const jvm_opc_dup2_x1 = 93
const jvm_opc_dup2_x2 = 94
const jvm_opc_swap = 95
const jvm_opc_iadd = 96
const jvm_opc_ladd = 97
const jvm_opc_fadd = 98
const jvm_opc_dadd = 99
const jvm_opc_isub = 100
const jvm_opc_lsub = 101
const jvm_opc_fsub = 102
const jvm_opc_dsub = 103
const jvm_opc_imul = 104
const jvm_opc_lmul = 105
const jvm_opc_fmul = 106
const jvm_opc_dmul = 107
const jvm_opc_idiv = 108
const jvm_opc_ldiv = 109
const jvm_opc_fdiv = 110
const jvm_opc_ddiv = 111
const jvm_opc_irem = 112
const jvm_opc_lrem = 113
const jvm_opc_frem = 114
const jvm_opc_drem = 115
const jvm_opc_ineg = 116
const jvm_opc_lneg = 117
const jvm_opc_fneg = 118
const jvm_opc_dneg = 119
const jvm_opc_ishl = 120
const jvm_opc_lshl = 121
const jvm_opc_ishr = 122
const jvm_opc_lshr = 123
const jvm_opc_iushr = 124
const jvm_opc_lushr = 125
const jvm_opc_iand = 126
const jvm_opc_land = 127
const jvm_opc_ior = 128
const jvm_opc_lor = 129
const jvm_opc_ixor = 130
const jvm_opc_lxor = 131
const jvm_opc_iinc = 132
const jvm_opc_i2l = 133
const jvm_opc_i2f = 134
const jvm_opc_i2d = 135
const jvm_opc_l2i = 136
const jvm_opc_l2f = 137
const jvm_opc_l2d = 138
const jvm_opc_f2i = 139
const jvm_opc_f2l = 140
const jvm_opc_f2d = 141
const jvm_opc_d2i = 142
const jvm_opc_d2l = 143
const jvm_opc_d2f = 144
const jvm_opc_i2b = 145
const jvm_opc_i2c = 146
const jvm_opc_i2s = 147
const jvm_opc_lcmp = 148
const jvm_opc_fcmpl = 149
const jvm_opc_fcmpg = 150
const jvm_opc_dcmpl = 151
const jvm_opc_dcmpg = 152
const jvm_opc_ifeq = 153
const jvm_opc_ifne = 154
const jvm_opc_iflt = 155
const jvm_opc_ifge = 156
const jvm_opc_ifgt = 157
const jvm_opc_ifle = 158
const jvm_opc_if_icmpeq = 159
const jvm_opc_if_icmpne = 160
const jvm_opc_if_icmplt = 161
const jvm_opc_if_icmpge = 162
const jvm_opc_if_icmpgt = 163
const jvm_opc_if_icmple = 164
const jvm_opc_if_acmpeq = 165
const jvm_opc_if_acmpne = 166
const jvm_opc_goto = 167
const jvm_opc_jsr = 168
const jvm_opc_ret = 169
const jvm_opc_tableswitch = 170
const jvm_opc_lookupswitch = 171
const jvm_opc_ireturn = 172
const jvm_opc_lreturn = 173
const jvm_opc_freturn = 174
const jvm_opc_dreturn = 175
const jvm_opc_areturn = 176
const jvm_opc_return = 177
const jvm_opc_getstatic = 178
const jvm_opc_putstatic = 179
const jvm_opc_getfield = 180
const jvm_opc_putfield = 181
const jvm_opc_invokevirtual = 182
const jvm_opc_invokespecial = 183
const jvm_opc_invokestatic = 184
const jvm_opc_invokeinterface = 185
const jvm_opc_invokedynamic = 186
const jvm_opc_new = 187
const jvm_opc_newarray = 188
const jvm_opc_anewarray = 189
const jvm_opc_arraylength = 190
const jvm_opc_athrow = 191
const jvm_opc_checkcast = 192
const jvm_opc_instanceof = 193
const jvm_opc_monitorenter = 194
const jvm_opc_monitorexit = 195
const jvm_opc_wide = 196
const jvm_opc_multianewarray = 197
const jvm_opc_ifnull = 198
const jvm_opc_ifnonnull = 199
const jvm_opc_goto_w = 200
const jvm_opc_jsr_w = 201
const jvm_opc_max = 201
